{
  "case_id": "case-4f8d8abf",
  "ticket_text": "[ORDER] shop several articles",
  "email_thread": [],
  "conversation_snippet": "Customer: shop several articles\nAgent: Thank you for your interest in shopping for several articles! I'm here to assist you in finding the perfect items that meet your requirements. To get started, could you please provide me with some details such as the type of articles you're looking for, any specific brands or styles you prefer, and your budget? This will help me tailor my recommendations and ensure a successful shopping experience for you. Let's make your shopping journey a delightful one!",
  "vip_tier": "unknown",
  "priority": "medium",
  "handle_time_minutes": 86.0,
  "churned_within_30d": false,
  "source_dataset": "bitext_dialogues (real)",
  "language": "en"
}